setup.cfg
setup.py
social_ids/__init__.py
social_ids.egg-info/PKG-INFO
social_ids.egg-info/SOURCES.txt
social_ids.egg-info/dependency_links.txt
social_ids.egg-info/entry_points.txt
social_ids.egg-info/requires.txt
social_ids.egg-info/top_level.txt
social_ids.egg-info/zip-safe
social_ids/cli/__init__.py
social_ids/cli/get_ids.py
social_ids/networks/__init__.py
social_ids/networks/facebook.py
social_ids/networks/instagram.py
social_ids/networks/twitter.py