Metadata-Version: 1.1
Name: social-ids
Version: 1.0
Summary: Get user ids from social network handlers
Home-page: https://github.com/guillermo-carrasco/social_ids
Author: Guillermo Carrasco
Author-email: guillermo@getfanzone.com
License: UNKNOWN
Keywords: Social Media,Facebook,Twitter,Instagram
Platform: UNKNOWN
Classifier: Programming Language :: Python
Classifier: Programming Language :: Python :: 3
